cnvm/__init__.py
cnvm/chemical_langevin_equation.py
cnvm/collective_variables.py
cnvm/model.py
cnvm/network_generator.py
cnvm/parameters.py
cnvm/utils.py
cnvm-0.2.0.dist-info/LICENSE
cnvm-0.2.0.dist-info/METADATA
cnvm-0.2.0.dist-info/WHEEL
cnvm-0.2.0.dist-info/RECORD
