Metadata-Version: 2.1
Name: cnvm
Version: 0.2.0
Summary: Continuous-time Noisy Voter Model (CNVM) of social dynamics.
Home-page: https://github.com/lueckem/cnvm
License: GPL-3.0-or-later
Keywords: voter model,social dynamics,opinion dynamics,statistical physics,agent-based model,epidemiology,interacting particle system
Author: Marvin Lücke
Requires-Python: >=3.9,<3.12
Classifier: Intended Audience :: Science/Research
Classifier: License :: OSI Approved :: GNU General Public License v3 or later (GPLv3+)
Classifier: Programming Language :: Python :: 3
Classifier: Programming Language :: Python :: 3.9
Classifier: Programming Language :: Python :: 3.10
Classifier: Programming Language :: Python :: 3.11
Classifier: Topic :: Scientific/Engineering :: Mathematics
Classifier: Topic :: Scientific/Engineering :: Physics
Requires-Dist: networkx (>=2.8.4)
Requires-Dist: numba (>=0.55)
Requires-Dist: numpy (>=1.21)
Requires-Dist: scipy (>=1.9.3)
Project-URL: Repository, https://github.com/lueckem/cnvm
